{
  "conditions": {
    "acceleration_flooring": "(acceleration_enabled && (flooring_layer_count > 0) && (bottom_layers > 0))",
    "acceleration_infill": "(acceleration_enabled && (infill_sparse_density > 0))",
    "acceleration_ironing": "(acceleration_enabled && ironing_enabled)",
    "acceleration_layer_0": "acceleration_enabled",
    "acceleration_prime_tower": "(prime_tower_enable && acceleration_enabled)",
    "acceleration_print": "acceleration_enabled",
    "acceleration_print_layer_0": "acceleration_enabled",
    "acceleration_roofing": "(acceleration_enabled && (roofing_layer_count > 0) && (top_layers > 0))",
    "acceleration_skirt_brim": "(acceleration_enabled && ((adhesion_type == \"skirt\") || (adhesion_type == \"brim\") || draft_shield_enabled || ooze_shield_enabled))",
    "acceleration_support": "(acceleration_enabled && (support_enable || support_meshes_present))",
    "acceleration_support_bottom": "(acceleration_enabled && support_bottom_enable && (support_enable || support_meshes_present))",
    "acceleration_support_infill": "(acceleration_enabled && (support_enable || support_meshes_present))",
    "acceleration_support_interface": "(acceleration_enabled && support_interface_enable && (support_enable || support_meshes_present))",
    "acceleration_support_roof": "(acceleration_enabled && support_roof_enable && (support_enable || support_meshes_present))",
    "acceleration_topbottom": "acceleration_enabled",
    "acceleration_travel": "(acceleration_enabled && acceleration_travel_enabled)",
    "acceleration_travel_enabled": "acceleration_enabled",
    "acceleration_travel_layer_0": "(acceleration_enabled && acceleration_travel_enabled)",
    "acceleration_wall": "acceleration_enabled",
    "acceleration_wall_0": "acceleration_enabled",
    "acceleration_wall_0_flooring": "(acceleration_enabled && (flooring_layer_count > 0) && (bottom_layers > 0))",
    "acceleration_wall_0_roofing": "(acceleration_enabled && (roofing_layer_count > 0) && (top_layers > 0))",
    "acceleration_wall_x": "acceleration_enabled",
    "acceleration_wall_x_flooring": "(acceleration_enabled && (flooring_layer_count > 0) && (bottom_layers > 0))",
    "acceleration_wall_x_roofing": "(acceleration_enabled && (roofing_layer_count > 0) && (top_layers > 0))",
    "adaptive_layer_height_threshold": "adaptive_layer_height_enabled",
    "adaptive_layer_height_variation": "adaptive_layer_height_enabled",
    "adaptive_layer_height_variation_step": "adaptive_layer_height_enabled",
    "adhesion_extruder_nr": "((extruders_enabled_count > 1) && (adhesion_type != \"none\"))",
    "alternate_carve_order": "(carve_multiple_volumes && extruderValues(\"magic_mesh_surface_mode\").every((p) => (p != \"surface\")))",
    "bottom_skin_expand_distance": "((top_layers > 0) || (bottom_layers > 0))",
    "bottom_skin_preshrink": "((top_layers > 0) || (bottom_layers > 0))",
    "bridge_enable_more_layers": "bridge_settings_enabled",
    "bridge_fan_speed": "bridge_settings_enabled",
    "bridge_fan_speed_2": "(bridge_settings_enabled && bridge_enable_more_layers)",
    "bridge_fan_speed_3": "(bridge_settings_enabled && bridge_enable_more_layers)",
    "bridge_interlace_lines": "bridge_settings_enabled",
    "bridge_skin_density": "bridge_settings_enabled",
    "bridge_skin_density_2": "(bridge_settings_enabled && bridge_enable_more_layers)",
    "bridge_skin_density_3": "(bridge_settings_enabled && bridge_enable_more_layers)",
    "bridge_skin_material_flow": "bridge_settings_enabled",
    "bridge_skin_material_flow_2": "(bridge_settings_enabled && bridge_enable_more_layers)",
    "bridge_skin_material_flow_3": "(bridge_settings_enabled && bridge_enable_more_layers)",
    "bridge_skin_speed": "bridge_settings_enabled",
    "bridge_skin_speed_2": "(bridge_settings_enabled && bridge_enable_more_layers)",
    "bridge_skin_speed_3": "(bridge_settings_enabled && bridge_enable_more_layers)",
    "bridge_skin_support_threshold": "bridge_settings_enabled",
    "bridge_wall_coast": "bridge_settings_enabled",
    "bridge_wall_material_flow": "bridge_settings_enabled",
    "bridge_wall_min_length": "bridge_settings_enabled",
    "bridge_wall_speed": "bridge_settings_enabled",
    "brim_gap": "(adhesion_type == \"brim\")",
    "brim_inside_margin": "(adhesion_type == \"brim\")",
    "brim_line_count": "(adhesion_type == \"brim\")",
    "brim_location": "(adhesion_type == \"brim\")",
    "brim_replaces_support": "((adhesion_type == \"brim\") && (support_enable || support_meshes_present))",
    "brim_smart_ordering": "(adhesion_type == \"brim\")",
    "brim_width": "(adhesion_type == \"brim\")",
    "build_fan_full_at_height": "(build_volume_fan_nr != 0)",
    "build_fan_full_layer": "(build_volume_fan_nr != 0)",
    "build_volume_fan_speed": "(build_volume_fan_nr != 0)",
    "build_volume_fan_speed_0": "(build_volume_fan_nr != 0)",
    "build_volume_temperature": "machine_heated_build_volume",
    "bv_temp_anomaly_limit": "ppr_enable",
    "bv_temp_warn_limit": "ppr_enable",
    "carve_multiple_volumes": "extruderValues(\"magic_mesh_surface_mode\").every((p) => (p != \"surface\"))",
    "center_object": "false",
    "coasting_min_volume": "coasting_enable",
    "coasting_speed": "coasting_enable",
    "coasting_volume": "coasting_enable",
    "conical_overhang_angle": "conical_overhang_enabled",
    "conical_overhang_hole_size": "conical_overhang_enabled",
    "connect_infill_polygons": "((infill_pattern != \"lightning\") && ((infill_pattern == \"cross\") || (infill_pattern == \"cross_3d\") || (infill_pattern == \"concentric\") || ((infill_multiplier % 2) == 0) || (infill_wall_line_count > 1)))",
    "connect_skin_polygons": "((((top_layers > 0) || (bottom_layers > 0)) && (top_bottom_pattern == \"concentric\")) || ((initial_bottom_layers > 0) && (top_bottom_pattern_0 == \"concentric\")) || ((roofing_layer_count > 0) && (roofing_pattern == \"concentric\")))",
    "cool_fan_speed": "cool_fan_enabled",
    "cool_fan_speed_0": "cool_fan_enabled",
    "cool_fan_speed_max": "cool_fan_enabled",
    "cool_fan_speed_min": "cool_fan_enabled",
    "cool_lift_head": "(cool_min_layer_time > 0)",
    "cool_min_layer_time_overhang": "(wall_overhang_angle < 90)",
    "cool_min_layer_time_overhang_min_segment_length": "(wall_overhang_angle < 90)",
    "cool_min_speed": "(cool_min_layer_time > 0)",
    "cool_min_temperature": "(cool_min_layer_time > 0)",
    "cross_infill_density_image": "((infill_pattern == \"cross\") || (infill_pattern == \"cross_3d\"))",
    "cross_infill_pocket_size": "(infill_pattern == \"cross_3d\")",
    "cross_support_density_image": "((support_pattern == \"cross\") || (support_pattern == \"cross_3d\"))",
    "default_material_bed_temperature": "false",
    "default_material_print_temperature": "false",
    "draft_shield_dist": "draft_shield_enabled",
    "draft_shield_height": "(draft_shield_enabled && (draft_shield_height_limitation == \"limited\"))",
    "draft_shield_height_limitation": "draft_shield_enabled",
    "expand_skins_expand_distance": "((top_layers > 0) || (bottom_layers > 0))",
    "extruder_prime_pos_x": "false",
    "extruder_prime_pos_y": "false",
    "flooring_angles": "((flooring_pattern != \"concentric\") && (flooring_layer_count > 0) && (bottom_layers > 0))",
    "flooring_extruder_nr": "((extruders_enabled_count > 1) && (Math.max(...extruderValues(\"flooring_layer_count\")) > 0) && (Math.max(...extruderValues(\"bottom_layers\")) > 0))",
    "flooring_layer_count": "(bottom_layers > 0)",
    "flooring_line_width": "((flooring_layer_count > 0) && (bottom_layers > 0))",
    "flooring_material_flow": "((flooring_layer_count > 0) && (bottom_layers > 0))",
    "flooring_monotonic": "((flooring_layer_count > 0) && (bottom_layers > 0) && (flooring_pattern != \"concentric\"))",
    "flooring_pattern": "((flooring_layer_count > 0) && (bottom_layers > 0))",
    "flow_anomaly_limit": "ppr_enable",
    "flow_warn_limit": "ppr_enable",
    "gradual_flow_discretisation_step_size": "gradual_flow_enabled",
    "gradual_infill_step_height": "((infill_sparse_density > 0) && (gradual_infill_steps > 0) && !([\"cubicsubdiv\", \"cross\", \"cross_3d\", \"lightning\"].includes(infill_pattern)))",
    "gradual_infill_steps": "((infill_sparse_density > 0) && !([\"cubicsubdiv\", \"cross\", \"cross_3d\", \"lightning\"].includes(infill_pattern)))",
    "gradual_support_infill_step_height": "((support_enable || support_meshes_present) && (support_infill_rate > 0) && (gradual_support_infill_steps > 0))",
    "gradual_support_infill_steps": "((support_enable || support_meshes_present) && (support_infill_rate > 0))",
    "hole_xy_offset_max_diameter": "(hole_xy_offset > 0)",
    "infill_angles": "(!([\"concentric\", \"cross\", \"cross_3d\", \"lightning\"].includes(infill_pattern)) && (infill_sparse_density > 0))",
    "infill_before_walls": "((infill_sparse_density > 0) && (wall_x_extruder_nr == infill_extruder_nr))",
    "infill_enable_travel_optimization": "(retraction_combing != \"off\")",
    "infill_end_move_inwards_length": "(infill_sparse_density > 0)",
    "infill_extruder_nr": "(extruders_enabled_count > 1)",
    "infill_line_width": "(infill_sparse_density > 0)",
    "infill_material_flow": "(infill_sparse_density > 0)",
    "infill_move_inwards_length": "(infill_sparse_density > 0)",
    "infill_multiplier": "((infill_sparse_density > 0) && (infill_pattern != \"zigzag\") && ((gradual_infill_steps == 0) || !(zig_zaggify_infill)))",
    "infill_offset_x": "((infill_pattern != \"lightning\") && ((infill_pattern == \"grid\") || (infill_pattern == \"lines\") || (infill_pattern == \"triangles\") || (infill_pattern == \"cubic\") || (infill_pattern == \"tetrahedral\") || (infill_pattern == \"quarter_cubic\") || (infill_pattern == \"zigzag\")))",
    "infill_offset_y": "((infill_pattern != \"lightning\") && ((infill_pattern == \"grid\") || (infill_pattern == \"lines\") || (infill_pattern == \"triangles\") || (infill_pattern == \"cubic\") || (infill_pattern == \"tetrahedral\") || (infill_pattern == \"quarter_cubic\") || (infill_pattern == \"zigzag\")))",
    "infill_overlap": "((infill_sparse_density > 0) && (infill_pattern != \"concentric\"))",
    "infill_overlap_mm": "((infill_sparse_density > 0) && (infill_pattern != \"concentric\"))",
    "infill_pattern": "(infill_line_distance > 0)",
    "infill_sparse_thickness": "(infill_sparse_density > 0)",
    "infill_start_move_inwards_length": "(infill_sparse_density > 0)",
    "infill_support_angle": "((infill_pattern != \"lightning\") && (infill_sparse_density > 0) && infill_support_enabled)",
    "infill_support_enabled": "((infill_pattern != \"lightning\") && (infill_sparse_density > 0))",
    "infill_wall_line_count": "(infill_sparse_density > 0)",
    "infill_wipe_dist": "(infill_sparse_density > 0)",
    "interlocking_beam_layer_count": "((extruders_enabled_count > 1) && interlocking_enable)",
    "interlocking_beam_width": "((extruders_enabled_count > 1) && interlocking_enable)",
    "interlocking_boundary_avoidance": "((extruders_enabled_count > 1) && interlocking_enable)",
    "interlocking_depth": "((extruders_enabled_count > 1) && interlocking_enable)",
    "interlocking_enable": "(extruders_enabled_count > 1)",
    "interlocking_orientation": "((extruders_enabled_count > 1) && interlocking_enable)",
    "ironing_flow": "ironing_enabled",
    "ironing_inset": "ironing_enabled",
    "ironing_line_spacing": "ironing_enabled",
    "ironing_monotonic": "(ironing_enabled && (ironing_pattern != \"concentric\"))",
    "ironing_only_highest_layer": "ironing_enabled",
    "ironing_pattern": "ironing_enabled",
    "jerk_flooring": "(jerk_enabled && (flooring_layer_count > 0) && (bottom_layers > 0))",
    "jerk_infill": "(jerk_enabled && (infill_sparse_density > 0))",
    "jerk_ironing": "(jerk_enabled && ironing_enabled)",
    "jerk_layer_0": "jerk_enabled",
    "jerk_prime_tower": "(prime_tower_enable && jerk_enabled)",
    "jerk_print": "jerk_enabled",
    "jerk_print_layer_0": "jerk_enabled",
    "jerk_roofing": "(jerk_enabled && (roofing_layer_count > 0) && (top_layers > 0))",
    "jerk_skirt_brim": "(jerk_enabled && ((adhesion_type == \"skirt\") || (adhesion_type == \"brim\") || draft_shield_enabled || ooze_shield_enabled))",
    "jerk_support": "(jerk_enabled && (support_enable || support_meshes_present))",
    "jerk_support_bottom": "(jerk_enabled && support_bottom_enable && (support_enable || support_meshes_present))",
    "jerk_support_infill": "(jerk_enabled && (support_enable || support_meshes_present))",
    "jerk_support_interface": "(jerk_enabled && support_interface_enable && (support_enable || support_meshes_present))",
    "jerk_support_roof": "(jerk_enabled && support_roof_enable && (support_enable || support_meshes_present))",
    "jerk_topbottom": "(((top_layers > 0) || (bottom_layers > 0)) && jerk_enabled)",
    "jerk_travel": "(jerk_enabled && jerk_travel_enabled)",
    "jerk_travel_enabled": "jerk_enabled",
    "jerk_travel_layer_0": "(jerk_enabled && jerk_travel_enabled)",
    "jerk_wall": "jerk_enabled",
    "jerk_wall_0": "jerk_enabled",
    "jerk_wall_0_flooring": "(jerk_enabled && (flooring_layer_count > 0) && (bottom_layers > 0))",
    "jerk_wall_0_roofing": "(jerk_enabled && (roofing_layer_count > 0) && (top_layers > 0))",
    "jerk_wall_x": "jerk_enabled",
    "jerk_wall_x_flooring": "(jerk_enabled && (flooring_layer_count > 0) && (bottom_layers > 0))",
    "jerk_wall_x_roofing": "(jerk_enabled && (roofing_layer_count > 0) && (top_layers > 0))",
    "keep_retracting_during_travel": "(retraction_enable && !(machine_firmware_retract) && (machine_gcode_flavor != \"UltiGCode\") && (machine_gcode_flavor != \"BFB\") && (retraction_during_travel_ratio > 0))",
    "layer_0_max_flow_acceleration": "gradual_flow_enabled",
    "layer_0_z_overlap": "(adhesion_type == \"raft\")",
    "layer_start_at_z_seam": "(z_seam_type == \"back\")",
    "lightning_infill_overhang_angle": "(infill_pattern == \"lightning\")",
    "lightning_infill_prune_angle": "(infill_pattern == \"lightning\")",
    "lightning_infill_straightening_angle": "(infill_pattern == \"lightning\")",
    "lightning_infill_support_angle": "(infill_pattern == \"lightning\")",
    "machine_extruders_shared_nozzle_initial_retraction": "machine_extruders_share_nozzle",
    "machine_min_cool_heat_time_window": "machine_nozzle_temp_enabled",
    "machine_nozzle_cool_down_speed": "machine_nozzle_temp_enabled",
    "machine_nozzle_heat_up_speed": "machine_nozzle_temp_enabled",
    "machine_scan_first_layer": "false",
    "magic_fuzzy_skin_enabled": "!(interlocking_enable)",
    "magic_fuzzy_skin_outside_only": "(magic_fuzzy_skin_enabled && !(interlocking_enable))",
    "magic_fuzzy_skin_point_density": "(magic_fuzzy_skin_enabled && !(interlocking_enable))",
    "magic_fuzzy_skin_point_dist": "(magic_fuzzy_skin_enabled && !(interlocking_enable))",
    "magic_fuzzy_skin_thickness": "(magic_fuzzy_skin_enabled && !(interlocking_enable))",
    "material_adhesion_tendency": "false",
    "material_anti_ooze_retracted_position": "false",
    "material_anti_ooze_retraction_speed": "false",
    "material_bed_temperature": "(machine_heated_bed && (machine_gcode_flavor != \"UltiGCode\"))",
    "material_bed_temperature_layer_0": "(machine_heated_bed && (machine_gcode_flavor != \"UltiGCode\"))",
    "material_brand": "false",
    "material_break_preparation_retracted_position": "false",
    "material_break_preparation_speed": "false",
    "material_break_preparation_temperature": "false",
    "material_break_retracted_position": "false",
    "material_break_speed": "false",
    "material_break_temperature": "false",
    "material_crystallinity": "false",
    "material_delta_temperature_roofing": "(machine_nozzle_temp_enabled && (roofing_layer_count > 0) && (top_layers > 0))",
    "material_diameter": "(machine_gcode_flavor != \"UltiGCode\")",
    "material_end_of_filament_purge_length": "false",
    "material_end_of_filament_purge_speed": "false",
    "material_extrusion_cool_down_speed": "((extruders_enabled_count > 1) && (material_final_print_temperature != material_print_temperature))",
    "material_final_print_temperature": "(machine_nozzle_temp_enabled && !(machine_extruders_share_heater))",
    "material_flow": "(machine_gcode_flavor != \"UltiGCode\")",
    "material_flow_temp_graph": "(false && machine_nozzle_temp_enabled)",
    "material_flush_purge_length": "false",
    "material_flush_purge_speed": "false",
    "material_guid": "false",
    "material_initial_print_temperature": "(machine_nozzle_temp_enabled && !(machine_extruders_share_heater))",
    "material_is_support_material": "false",
    "material_max_flowrate": "false",
    "material_maximum_park_duration": "false",
    "material_no_load_move_factor": "false",
    "material_pressure_advance_factor": "false",
    "material_print_temp_prepend": "machine_nozzle_temp_enabled",
    "material_print_temp_wait": "machine_nozzle_temp_enabled",
    "material_print_temperature": "machine_nozzle_temp_enabled",
    "material_print_temperature_layer_0": "machine_nozzle_temp_enabled",
    "material_standby_temperature": "((extruders_enabled_count > 1) && machine_nozzle_temp_enabled)",
    "material_surface_energy": "false",
    "material_type": "false",
    "max_extrusion_before_wipe": "clean_between_layers",
    "max_flow_acceleration": "gradual_flow_enabled",
    "max_skin_angle_for_expansion": "(((top_layers > 0) || (bottom_layers > 0)) && ((top_skin_expand_distance > 0) || (bottom_skin_expand_distance > 0)))",
    "mesh_position_x": "false",
    "mesh_position_y": "false",
    "mesh_position_z": "false",
    "mesh_rotation_matrix": "false",
    "meshfix_fluid_motion_angle": "meshfix_fluid_motion_enabled",
    "meshfix_fluid_motion_shift_distance": "meshfix_fluid_motion_enabled",
    "meshfix_fluid_motion_small_distance": "meshfix_fluid_motion_enabled",
    "min_bead_width": "fill_outline_gaps",
    "min_feature_size": "fill_outline_gaps",
    "min_skin_width_for_expansion": "(((top_layers > 0) || (bottom_layers > 0)) && ((top_skin_expand_distance > 0) || (bottom_skin_expand_distance > 0)))",
    "minimum_bottom_area": "(support_bottom_enable && ((support_enable && (support_structure == \"normal\")) || support_meshes_present))",
    "minimum_interface_area": "(support_interface_enable && (support_enable || support_meshes_present))",
    "minimum_roof_area": "(support_roof_enable && (support_enable || support_meshes_present))",
    "minimum_support_area": "(support_enable || support_meshes_present)",
    "mold_angle": "mold_enabled",
    "mold_roof_height": "mold_enabled",
    "mold_width": "mold_enabled",
    "multi_material_paint_depth": "(extruders_enabled_count > 1)",
    "multi_material_paint_resolution": "(extruders_enabled_count > 1)",
    "ooze_shield_angle": "ooze_shield_enabled",
    "ooze_shield_dist": "ooze_shield_enabled",
    "ooze_shield_enabled": "(extruders_enabled_count > 1)",
    "ppr_enable": "false",
    "prime_blob_enable": "false",
    "prime_during_travel_ratio": "(retraction_enable && !(machine_firmware_retract) && (machine_gcode_flavor != \"UltiGCode\") && (machine_gcode_flavor != \"BFB\"))",
    "prime_tower_base_curve_magnitude": "(prime_tower_enable && (prime_tower_brim_enable || (adhesion_type == \"raft\")))",
    "prime_tower_base_height": "(prime_tower_enable && (prime_tower_brim_enable || (adhesion_type == \"raft\")))",
    "prime_tower_base_size": "(prime_tower_enable && (prime_tower_brim_enable || (adhesion_type == \"raft\")))",
    "prime_tower_brim_enable": "(prime_tower_enable && (adhesion_type != \"raft\"))",
    "prime_tower_enable": "(extruders_enabled_count > 1)",
    "prime_tower_line_width": "prime_tower_enable",
    "prime_tower_max_bridging_distance": "prime_tower_enable",
    "prime_tower_min_shell_thickness": "(prime_tower_enable && (prime_tower_mode == \"interleaved\"))",
    "prime_tower_min_volume": "prime_tower_enable",
    "prime_tower_mode": "prime_tower_enable",
    "prime_tower_position_x": "prime_tower_enable",
    "prime_tower_position_y": "prime_tower_enable",
    "prime_tower_raft_base_line_spacing": "(prime_tower_enable && (adhesion_type == \"raft\"))",
    "prime_tower_size": "prime_tower_enable",
    "prime_tower_wipe_enabled": "prime_tower_enable",
    "print_sequence": "(extruders_enabled_count == 1)",
    "print_temp_anomaly_limit": "ppr_enable",
    "print_temp_warn_limit": "ppr_enable",
    "raft_acceleration": "((adhesion_type == \"raft\") && acceleration_enabled)",
    "raft_airgap": "(adhesion_type == \"raft\")",
    "raft_base_acceleration": "((adhesion_type == \"raft\") && acceleration_enabled)",
    "raft_base_extruder_nr": "((extruders_enabled_count > 1) && (adhesion_type == \"raft\"))",
    "raft_base_fan_speed": "(adhesion_type == \"raft\")",
    "raft_base_flow": "(adhesion_type == \"raft\")",
    "raft_base_infill_overlap": "(adhesion_type == \"raft\")",
    "raft_base_infill_overlap_mm": "(adhesion_type == \"raft\")",
    "raft_base_jerk": "((adhesion_type == \"raft\") && jerk_enabled)",
    "raft_base_line_spacing": "(adhesion_type == \"raft\")",
    "raft_base_line_width": "(adhesion_type == \"raft\")",
    "raft_base_margin": "(adhesion_type == \"raft\")",
    "raft_base_remove_inside_corners": "(adhesion_type == \"raft\")",
    "raft_base_smoothing": "((adhesion_type == \"raft\") && !(raft_base_remove_inside_corners))",
    "raft_base_speed": "(adhesion_type == \"raft\")",
    "raft_base_thickness": "(adhesion_type == \"raft\")",
    "raft_base_wall_count": "(adhesion_type == \"raft\")",
    "raft_fan_speed": "(adhesion_type == \"raft\")",
    "raft_flow": "(adhesion_type == \"raft\")",
    "raft_interface_acceleration": "((adhesion_type == \"raft\") && acceleration_enabled && (raft_interface_layers > 0))",
    "raft_interface_extruder_nr": "((extruders_enabled_count > 1) && (adhesion_type == \"raft\"))",
    "raft_interface_fan_speed": "((adhesion_type == \"raft\") && (raft_interface_layers > 0))",
    "raft_interface_flow": "(adhesion_type == \"raft\")",
    "raft_interface_infill_overlap": "(adhesion_type == \"raft\")",
    "raft_interface_infill_overlap_mm": "(adhesion_type == \"raft\")",
    "raft_interface_jerk": "((adhesion_type == \"raft\") && jerk_enabled && (raft_interface_layers > 0))",
    "raft_interface_layers": "(adhesion_type == \"raft\")",
    "raft_interface_line_spacing": "((adhesion_type == \"raft\") && (raft_interface_layers > 0))",
    "raft_interface_line_width": "((adhesion_type == \"raft\") && (raft_interface_layers > 0))",
    "raft_interface_margin": "(adhesion_type == \"raft\")",
    "raft_interface_remove_inside_corners": "(adhesion_type == \"raft\")",
    "raft_interface_smoothing": "((adhesion_type == \"raft\") && !(raft_interface_remove_inside_corners))",
    "raft_interface_speed": "((adhesion_type == \"raft\") && (raft_interface_layers > 0))",
    "raft_interface_thickness": "((adhesion_type == \"raft\") && (raft_interface_layers > 0))",
    "raft_interface_wall_count": "(adhesion_type == \"raft\")",
    "raft_interface_z_offset": "((adhesion_type == \"raft\") && (raft_interface_layers > 0))",
    "raft_jerk": "((adhesion_type == \"raft\") && jerk_enabled)",
    "raft_margin": "(adhesion_type == \"raft\")",
    "raft_remove_inside_corners": "(adhesion_type == \"raft\")",
    "raft_smoothing": "((adhesion_type == \"raft\") && !(raft_remove_inside_corners))",
    "raft_speed": "(adhesion_type == \"raft\")",
    "raft_surface_acceleration": "((adhesion_type == \"raft\") && acceleration_enabled && (raft_surface_layers > 0))",
    "raft_surface_extruder_nr": "((extruders_enabled_count > 1) && (adhesion_type == \"raft\"))",
    "raft_surface_fan_speed": "((adhesion_type == \"raft\") && (raft_surface_layers > 0))",
    "raft_surface_flow": "(adhesion_type == \"raft\")",
    "raft_surface_infill_overlap": "(adhesion_type == \"raft\")",
    "raft_surface_infill_overlap_mm": "(adhesion_type == \"raft\")",
    "raft_surface_jerk": "((adhesion_type == \"raft\") && jerk_enabled && (raft_surface_layers > 0))",
    "raft_surface_layers": "(adhesion_type == \"raft\")",
    "raft_surface_line_spacing": "((adhesion_type == \"raft\") && (raft_surface_layers > 0))",
    "raft_surface_line_width": "((adhesion_type == \"raft\") && (raft_surface_layers > 0))",
    "raft_surface_margin": "(adhesion_type == \"raft\")",
    "raft_surface_monotonic": "((adhesion_type == \"raft\") && (raft_surface_layers > 0))",
    "raft_surface_remove_inside_corners": "(adhesion_type == \"raft\")",
    "raft_surface_smoothing": "((adhesion_type == \"raft\") && !(raft_surface_remove_inside_corners))",
    "raft_surface_speed": "((adhesion_type == \"raft\") && (raft_surface_layers > 0))",
    "raft_surface_thickness": "((adhesion_type == \"raft\") && (raft_surface_layers > 0))",
    "raft_surface_wall_count": "(adhesion_type == \"raft\")",
    "raft_surface_z_offset": "((adhesion_type == \"raft\") && (raft_surface_layers > 0))",
    "raft_wall_count": "(adhesion_type == \"raft\")",
    "remove_empty_first_layers": "!((support_enable || support_meshes_present))",
    "reset_flow_duration": "gradual_flow_enabled",
    "retraction_amount": "(retraction_enable && (machine_gcode_flavor != \"UltiGCode\"))",
    "retraction_combing_avoid_distance": "(retraction_combing != \"off\")",
    "retraction_combing_max_distance": "(retraction_combing != \"off\")",
    "retraction_count_max": "retraction_enable",
    "retraction_during_travel_ratio": "(retraction_enable && !(machine_firmware_retract) && (machine_gcode_flavor != \"UltiGCode\") && (machine_gcode_flavor != \"BFB\"))",
    "retraction_extra_prime_amount": "retraction_enable",
    "retraction_extrusion_window": "retraction_enable",
    "retraction_hop": "(retraction_enable && retraction_hop_enabled)",
    "retraction_hop_after_extruder_switch": "(retraction_hop_enabled && (extruders_enabled_count > 1))",
    "retraction_hop_after_extruder_switch_height": "(retraction_enable && retraction_hop_after_extruder_switch && (extruders_enabled_count > 1))",
    "retraction_hop_enabled": "retraction_enable",
    "retraction_hop_only_when_collides": "(retraction_enable && retraction_hop_enabled && travel_avoid_other_parts)",
    "retraction_prime_speed": "(retraction_enable && (machine_gcode_flavor != \"UltiGCode\"))",
    "retraction_retract_speed": "(retraction_enable && (machine_gcode_flavor != \"UltiGCode\"))",
    "retraction_speed": "(retraction_enable && (machine_gcode_flavor != \"UltiGCode\"))",
    "roofing_angles": "((roofing_pattern != \"concentric\") && (roofing_layer_count > 0) && (top_layers > 0))",
    "roofing_expansion": "((roofing_layer_count > 0) && (top_layers > 0))",
    "roofing_extruder_nr": "((extruders_enabled_count > 1) && (Math.max(...extruderValues(\"roofing_layer_count\")) > 0) && (Math.max(...extruderValues(\"top_layers\")) > 0))",
    "roofing_layer_count": "(top_layers > 0)",
    "roofing_line_width": "((roofing_layer_count > 0) && (top_layers > 0))",
    "roofing_material_flow": "((roofing_layer_count > 0) && (top_layers > 0))",
    "roofing_monotonic": "((roofing_layer_count > 0) && (top_layers > 0) && (roofing_pattern != \"concentric\"))",
    "roofing_pattern": "((roofing_layer_count > 0) && (top_layers > 0))",
    "scarf_joint_seam_start_height_ratio": "(scarf_joint_seam_length > 0)",
    "scarf_split_distance": "(scarf_joint_seam_length > 0)",
    "skin_angles": "(((top_layers > 0) || (bottom_layers > 0)) && (top_bottom_pattern != \"concentric\"))",
    "skin_line_width": "((top_layers > 0) || (bottom_layers > 0))",
    "skin_material_flow": "((top_layers > 0) || (bottom_layers > 0))",
    "skin_material_flow_layer_0": "(bottom_layers > 0)",
    "skin_monotonic": "(((top_layers > 0) || (bottom_layers > 0)) && ((top_bottom_pattern != \"concentric\") || (top_bottom_pattern_0 != \"concentric\")))",
    "skin_no_small_gaps_heuristic": "((top_layers > 0) || (bottom_layers > 0))",
    "skin_outline_count": "(((top_layers > 0) || (bottom_layers > 0)) && ((top_bottom_pattern != \"concentric\") || (top_bottom_pattern_0 != \"concentric\") || ((roofing_layer_count > 0) && (roofing_pattern != \"concentric\"))))",
    "skin_overlap": "(((top_layers > 0) || (bottom_layers > 0)) && (top_bottom_pattern != \"concentric\"))",
    "skin_overlap_mm": "(((top_layers > 0) || (bottom_layers > 0)) && (top_bottom_pattern != \"concentric\"))",
    "skin_preshrink": "((top_layers > 0) || (bottom_layers > 0))",
    "skin_support": "((infill_sparse_density > 0) && (top_layers > 0))",
    "skin_support_density": "skin_support",
    "skin_support_fan_speed": "skin_support",
    "skin_support_interlace_lines": "skin_support",
    "skin_support_material_flow": "skin_support",
    "skin_support_speed": "skin_support",
    "skirt_brim_extruder_nr": "((extruders_enabled_count > 1) && [\"skirt\", \"brim\"].includes(adhesion_type))",
    "skirt_brim_line_width": "((adhesion_type == \"skirt\") || (adhesion_type == \"brim\") || draft_shield_enabled || ooze_shield_enabled)",
    "skirt_brim_material_flow": "((adhesion_type == \"skirt\") || (adhesion_type == \"brim\") || draft_shield_enabled || ooze_shield_enabled)",
    "skirt_brim_minimal_length": "((adhesion_type == \"skirt\") || (adhesion_type == \"brim\"))",
    "skirt_brim_speed": "((adhesion_type == \"skirt\") || (adhesion_type == \"brim\") || draft_shield_enabled || ooze_shield_enabled)",
    "skirt_gap": "(adhesion_type == \"skirt\")",
    "skirt_height": "(adhesion_type == \"skirt\")",
    "skirt_line_count": "(adhesion_type == \"skirt\")",
    "small_feature_max_length": "(small_hole_max_size > 0)",
    "small_feature_speed_factor": "(small_hole_max_size > 0)",
    "small_feature_speed_factor_0": "(small_hole_max_size > 0)",
    "small_skin_on_surface": "((small_skin_width > 0) && (top_layers > 0))",
    "small_skin_width": "(((top_layers > 0) || (bottom_layers > 0)) && (top_bottom_pattern != \"concentric\"))",
    "smooth_spiralized_contours": "magic_spiralize",
    "speed_flooring": "((flooring_layer_count > 0) && (bottom_layers > 0))",
    "speed_infill": "(infill_sparse_density > 0)",
    "speed_ironing": "ironing_enabled",
    "speed_layer_0": "(speed_slowdown_layers > 0)",
    "speed_prime_tower": "prime_tower_enable",
    "speed_print_layer_0": "(speed_slowdown_layers > 0)",
    "speed_roofing": "((roofing_layer_count > 0) && (top_layers > 0))",
    "speed_support": "(support_enable || support_meshes_present)",
    "speed_support_bottom": "(support_bottom_enable && (support_enable || support_meshes_present))",
    "speed_support_infill": "(support_enable || support_meshes_present)",
    "speed_support_interface": "(support_interface_enable && (support_enable || support_meshes_present))",
    "speed_support_roof": "(support_roof_enable && (support_enable || support_meshes_present))",
    "speed_topbottom": "((top_layers > 0) || (bottom_layers > 0))",
    "speed_travel_layer_0": "(speed_slowdown_layers > 0)",
    "speed_wall_0_flooring": "((flooring_layer_count > 0) && (bottom_layers > 0))",
    "speed_wall_0_roofing": "((roofing_layer_count > 0) && (top_layers > 0))",
    "speed_wall_x_flooring": "((flooring_layer_count > 0) && (bottom_layers > 0))",
    "speed_wall_x_roofing": "((roofing_layer_count > 0) && (top_layers > 0))",
    "sub_div_rad_add": "((infill_sparse_density > 0) && (infill_pattern == \"cubicsubdiv\"))",
    "support_angle": "support_enable",
    "support_bottom_angles": "((support_enable || support_meshes_present) && support_bottom_enable && (support_bottom_pattern != \"concentric\"))",
    "support_bottom_density": "(support_bottom_enable && (support_enable || support_meshes_present))",
    "support_bottom_distance": "((support_enable || support_meshes_present) && (support_type == \"everywhere\"))",
    "support_bottom_enable": "((support_enable || support_meshes_present) && support_interface_enable)",
    "support_bottom_extruder_nr": "((support_enable || support_meshes_present) && (extruders_enabled_count > 1) && support_bottom_enable)",
    "support_bottom_height": "(support_bottom_enable && (support_enable || support_meshes_present))",
    "support_bottom_line_distance": "(support_bottom_enable && (support_enable || support_meshes_present))",
    "support_bottom_line_width": "((support_enable || support_meshes_present) && support_bottom_enable)",
    "support_bottom_material_flow": "((support_enable || support_meshes_present) && support_bottom_enable)",
    "support_bottom_offset": "(support_bottom_enable && (support_enable || support_meshes_present))",
    "support_bottom_pattern": "(support_bottom_enable && (support_enable || support_meshes_present))",
    "support_bottom_stair_step_height": "((support_enable && (support_structure == \"normal\")) || support_meshes_present)",
    "support_bottom_stair_step_min_slope": "(((support_enable && (support_structure == \"normal\")) || support_meshes_present) && (support_bottom_stair_step_height > 0))",
    "support_bottom_stair_step_width": "(((support_enable && (support_structure == \"normal\")) || support_meshes_present) && (support_bottom_stair_step_height > 0))",
    "support_bottom_wall_count": "((support_enable && support_interface_enable) || support_meshes_present)",
    "support_brim_enable": "(support_enable || support_meshes_present)",
    "support_brim_line_count": "((support_enable || support_meshes_present) && support_brim_enable)",
    "support_brim_minimum_hole_area": "support_brim_enable",
    "support_brim_width": "((support_enable || support_meshes_present) && support_brim_enable)",
    "support_conical_angle": "(support_conical_enabled && support_enable && (support_structure != \"tree\"))",
    "support_conical_enabled": "(support_enable && (support_structure != \"tree\"))",
    "support_conical_min_width": "(support_conical_enabled && support_enable && (support_structure != \"tree\") && (support_conical_angle > 0))",
    "support_connect_zigzags": "((support_enable || support_meshes_present) && (support_pattern == \"zigzag\"))",
    "support_extruder_nr": "((support_enable || support_meshes_present) && (extruders_enabled_count > 1))",
    "support_extruder_nr_layer_0": "((support_enable || support_meshes_present) && (extruders_enabled_count > 1))",
    "support_fan_enable": "(support_enable || support_meshes_present)",
    "support_infill_angles": "((support_enable || support_meshes_present) && (support_pattern != \"concentric\") && (support_infill_rate > 0))",
    "support_infill_density_multiplier_initial_layer": "((support_enable || support_meshes_present) && (support_line_distance > 0) && (support_pattern != \"lightning\"))",
    "support_infill_extruder_nr": "((support_enable || support_meshes_present) && (extruders_enabled_count > 1))",
    "support_infill_multiplier": "((support_enable || support_meshes_present) && (support_line_distance > 0) && (support_pattern != \"zigzag\"))",
    "support_infill_rate": "(support_enable || support_meshes_present)",
    "support_infill_sparse_thickness": "((support_enable || support_meshes_present) && (support_infill_rate > 0))",
    "support_initial_layer_line_distance": "(support_enable || support_meshes_present)",
    "support_interface_angles": "((support_enable || support_meshes_present) && support_interface_enable && (support_interface_pattern != \"concentric\"))",
    "support_interface_density": "(support_interface_enable && (support_enable || support_meshes_present))",
    "support_interface_enable": "(support_enable || support_meshes_present)",
    "support_interface_extruder_nr": "((support_enable || support_meshes_present) && (extruders_enabled_count > 1) && support_interface_enable)",
    "support_interface_height": "(support_interface_enable && (support_enable || support_meshes_present))",
    "support_interface_line_width": "((support_enable || support_meshes_present) && support_interface_enable)",
    "support_interface_material_flow": "((support_enable || support_meshes_present) && support_interface_enable)",
    "support_interface_offset": "(support_interface_enable && (support_enable || support_meshes_present))",
    "support_interface_pattern": "(support_interface_enable && (support_enable || support_meshes_present))",
    "support_interface_priority": "(support_enable && (support_structure == \"tree\") && support_roof_enable)",
    "support_interface_wall_count": "((support_enable && support_interface_enable) || support_meshes_present)",
    "support_join_distance": "((support_enable && (support_structure == \"normal\")) || support_meshes_present)",
    "support_lightning_angle": "((support_enable || support_meshes_present) && (support_line_distance > 0) && (support_pattern == \"lightning\"))",
    "support_lightning_overhang_angle": "((support_enable || support_meshes_present) && (support_line_distance > 0) && (support_pattern == \"lightning\"))",
    "support_lightning_prune_angle": "((support_enable || support_meshes_present) && (support_line_distance > 0) && (support_pattern == \"lightning\"))",
    "support_lightning_straightening_angle": "((support_enable || support_meshes_present) && (support_line_distance > 0) && (support_pattern == \"lightning\"))",
    "support_line_distance": "(support_enable || support_meshes_present)",
    "support_line_width": "(support_enable || support_meshes_present)",
    "support_material_flow": "(support_enable || support_meshes_present)",
    "support_mesh_drop_down": "support_mesh",
    "support_meshes_present": "false",
    "support_offset": "((support_enable || support_meshes_present) && (support_structure == \"normal\"))",
    "support_pattern": "((support_enable || support_meshes_present) && (support_infill_rate > 0))",
    "support_roof_angles": "((support_enable || support_meshes_present) && support_roof_enable && (support_roof_pattern != \"concentric\"))",
    "support_roof_density": "(support_roof_enable && (support_enable || support_meshes_present))",
    "support_roof_enable": "((support_enable || support_meshes_present) && support_interface_enable)",
    "support_roof_extruder_nr": "((support_enable || support_meshes_present) && (extruders_enabled_count > 1) && support_roof_enable)",
    "support_roof_height": "(support_roof_enable && (support_enable || support_meshes_present))",
    "support_roof_line_distance": "(support_roof_enable && (support_enable || support_meshes_present))",
    "support_roof_line_width": "((support_enable || support_meshes_present) && support_roof_enable)",
    "support_roof_material_flow": "((support_enable || support_meshes_present) && support_roof_enable)",
    "support_roof_offset": "(support_roof_enable && (support_enable || support_meshes_present))",
    "support_roof_pattern": "(support_roof_enable && (support_enable || support_meshes_present))",
    "support_roof_wall_count": "((support_enable && support_interface_enable) || support_meshes_present)",
    "support_skip_some_zags": "((support_enable || support_meshes_present) && (support_pattern == \"zigzag\"))",
    "support_skip_zag_per_mm": "((support_enable || support_meshes_present) && (support_pattern == \"zigzag\") && support_skip_some_zags)",
    "support_structure": "support_enable",
    "support_supported_skin_fan_speed": "((support_enable || support_meshes_present) && support_fan_enable)",
    "support_top_distance": "(support_enable || support_meshes_present)",
    "support_tower_diameter": "(support_enable && (support_structure == \"normal\") && support_use_towers)",
    "support_tower_maximum_supported_diameter": "(support_enable && (support_structure == \"normal\") && support_use_towers)",
    "support_tower_roof_angle": "(support_enable && (support_structure == \"normal\") && support_use_towers)",
    "support_tree_angle": "(support_enable && (support_structure == \"tree\"))",
    "support_tree_angle_slow": "(support_enable && (support_structure == \"tree\"))",
    "support_tree_bp_diameter": "(support_enable && (support_structure == \"tree\"))",
    "support_tree_branch_diameter": "(support_enable && (support_structure == \"tree\"))",
    "support_tree_branch_diameter_angle": "(support_enable && (support_structure == \"tree\"))",
    "support_tree_branch_reach_limit": "(support_enable && support_tree_limit_branch_reach && (support_structure == \"tree\"))",
    "support_tree_limit_branch_reach": "(support_enable && (support_structure == \"tree\"))",
    "support_tree_max_diameter": "(support_enable && (support_structure == \"tree\"))",
    "support_tree_max_diameter_increase_by_merges_when_support_to_model": "(support_enable && (support_structure == \"tree\") && (support_type == \"everywhere\"))",
    "support_tree_min_height_to_model": "(support_enable && (support_structure == \"tree\") && (support_type == \"everywhere\"))",
    "support_tree_rest_preference": "(support_enable && (support_structure == \"tree\") && (support_type == \"everywhere\"))",
    "support_tree_tip_diameter": "(support_enable && (support_structure == \"tree\"))",
    "support_tree_top_rate": "(support_enable && (support_structure == \"tree\"))",
    "support_type": "support_enable",
    "support_use_towers": "(support_enable && (support_structure == \"normal\"))",
    "support_wall_count": "(support_enable || support_meshes_present)",
    "support_xy_distance": "(support_enable || support_meshes_present)",
    "support_xy_distance_overhang": "((support_enable || support_meshes_present) && (support_xy_overrides_z == \"z_overrides_xy\"))",
    "support_xy_overrides_z": "(support_enable || support_meshes_present)",
    "support_z_distance": "(support_enable || support_meshes_present)",
    "support_z_seam_away_from_model": "support_enable",
    "support_z_seam_min_distance": "(support_z_seam_away_from_model && support_enable)",
    "support_zag_skip_count": "((support_enable || support_meshes_present) && (support_pattern == \"zigzag\") && support_skip_some_zags)",
    "switch_extruder_extra_prime_amount": "(retraction_enable && (extruders_enabled_count > 1))",
    "switch_extruder_prime_speed": "(retraction_enable && (extruders_enabled_count > 1))",
    "switch_extruder_retraction_amount": "(retraction_enable && (extruders_enabled_count > 1))",
    "switch_extruder_retraction_speed": "(retraction_enable && (extruders_enabled_count > 1))",
    "switch_extruder_retraction_speeds": "(retraction_enable && (extruders_enabled_count > 1))",
    "top_bottom_extruder_nr": "(extruders_enabled_count > 1)",
    "top_bottom_pattern": "((top_layers > 0) || (bottom_layers > 0))",
    "top_bottom_pattern_0": "((top_layers > 0) || (bottom_layers > 0))",
    "top_skin_expand_distance": "((top_layers > 0) || (bottom_layers > 0))",
    "top_skin_preshrink": "((top_layers > 0) || (bottom_layers > 0))",
    "travel_avoid_distance": "((retraction_combing != \"off\") && travel_avoid_other_parts)",
    "travel_avoid_other_parts": "(retraction_combing != \"off\")",
    "travel_avoid_supports": "((retraction_combing != \"off\") && travel_avoid_other_parts)",
    "travel_retract_before_outer_wall": "retraction_enable",
    "user_defined_print_order_enabled": "(print_sequence == \"one_at_a_time\")",
    "wall_0_acceleration": "(wall_0_start_speed_ratio < 100.0)",
    "wall_0_deceleration": "(wall_0_end_speed_ratio < 100.0)",
    "wall_0_extruder_nr": "(extruders_enabled_count > 1)",
    "wall_0_material_flow_flooring": "((flooring_layer_count > 0) && (bottom_layers > 0))",
    "wall_0_material_flow_roofing": "((roofing_layer_count > 0) && (top_layers > 0))",
    "wall_extruder_nr": "(extruders_enabled_count > 1)",
    "wall_overhang_speed_factors": "(wall_overhang_angle < 90)",
    "wall_transition_filter_distance": "false",
    "wall_x_extruder_nr": "(extruders_enabled_count > 1)",
    "wall_x_material_flow_flooring": "((flooring_layer_count > 0) && (bottom_layers > 0))",
    "wall_x_material_flow_roofing": "((roofing_layer_count > 0) && (top_layers > 0))",
    "wipe_brush_pos_x": "clean_between_layers",
    "wipe_hop_amount": "(wipe_hop_enable && clean_between_layers)",
    "wipe_hop_enable": "clean_between_layers",
    "wipe_hop_speed": "(wipe_hop_enable && clean_between_layers)",
    "wipe_move_distance": "clean_between_layers",
    "wipe_pause": "clean_between_layers",
    "wipe_repeat_count": "clean_between_layers",
    "wipe_retraction_amount": "(wipe_retraction_enable && clean_between_layers)",
    "wipe_retraction_enable": "clean_between_layers",
    "wipe_retraction_extra_prime_amount": "(wipe_retraction_enable && clean_between_layers)",
    "wipe_retraction_prime_speed": "(wipe_retraction_enable && clean_between_layers)",
    "wipe_retraction_retract_speed": "(wipe_retraction_enable && clean_between_layers)",
    "wipe_retraction_speed": "(wipe_retraction_enable && clean_between_layers)",
    "z_seam_corner": "(z_seam_type == \"sharpest_corner\")",
    "z_seam_on_vertex": "((z_seam_type == \"back\") || (z_seam_type == \"shortest\"))",
    "z_seam_position": "(z_seam_type == \"back\")",
    "z_seam_relative": "(z_seam_type == \"back\")",
    "z_seam_x": "(z_seam_type == \"back\")",
    "z_seam_y": "(z_seam_type == \"back\")",
    "zig_zaggify_infill": "((infill_pattern == \"lines\") || (infill_pattern == \"grid\") || (infill_pattern == \"triangles\") || (infill_pattern == \"trihexagon\") || (infill_pattern == \"cubic\") || (infill_pattern == \"tetrahedral\") || (infill_pattern == \"quarter_cubic\") || (infill_pattern == \"cross\") || (infill_pattern == \"cross_3d\") || (infill_pattern == \"gyroid\") || (infill_pattern == \"honeycomb\") || (infill_pattern == \"octagon\"))",
    "zig_zaggify_support": "((support_enable || support_meshes_present) && ((support_pattern == \"lines\") || (support_pattern == \"grid\") || (support_pattern == \"triangles\") || (support_pattern == \"cross\") || (support_pattern == \"gyroid\") || (support_pattern == \"honeycomb\") || (support_pattern == \"octagon\")))"
  },
  "functions": [
    "extruderValues"
  ],
  "variable_defaults": {
    "acceleration_enabled": false,
    "acceleration_travel_enabled": true,
    "adaptive_layer_height_enabled": false,
    "adhesion_type": "brim",
    "bottom_layers": 6,
    "bottom_skin_expand_distance": 1,
    "bridge_enable_more_layers": true,
    "bridge_settings_enabled": false,
    "build_volume_fan_nr": 0,
    "carve_multiple_volumes": true,
    "clean_between_layers": false,
    "coasting_enable": false,
    "conical_overhang_enabled": false,
    "cool_fan_enabled": true,
    "cool_min_layer_time": 5,
    "draft_shield_enabled": false,
    "draft_shield_height_limitation": "full",
    "extruders_enabled_count": 1,
    "fill_outline_gaps": true,
    "flooring_layer_count": 0,
    "flooring_pattern": "lines",
    "gradual_flow_enabled": false,
    "gradual_infill_steps": 0,
    "gradual_support_infill_steps": 0,
    "hole_xy_offset": 0,
    "infill_extruder_nr": -1,
    "infill_line_distance": 2,
    "infill_multiplier": 1,
    "infill_pattern": "grid",
    "infill_sparse_density": 20,
    "infill_support_enabled": false,
    "infill_wall_line_count": 0,
    "initial_bottom_layers": 6,
    "interlocking_enable": false,
    "ironing_enabled": false,
    "ironing_pattern": "zigzag",
    "jerk_enabled": false,
    "jerk_travel_enabled": true,
    "machine_extruders_share_heater": false,
    "machine_extruders_share_nozzle": false,
    "machine_firmware_retract": false,
    "machine_gcode_flavor": "RepRap (Marlin/Sprinter)",
    "machine_heated_bed": false,
    "machine_heated_build_volume": false,
    "machine_nozzle_temp_enabled": true,
    "magic_fuzzy_skin_enabled": false,
    "magic_spiralize": false,
    "material_final_print_temperature": 195,
    "material_print_temperature": 210,
    "meshfix_fluid_motion_enabled": true,
    "mold_enabled": false,
    "ooze_shield_enabled": false,
    "ppr_enable": false,
    "prime_tower_brim_enable": false,
    "prime_tower_enable": false,
    "prime_tower_mode": "normal",
    "print_sequence": "all_at_once",
    "raft_base_remove_inside_corners": false,
    "raft_interface_layers": 1,
    "raft_interface_remove_inside_corners": false,
    "raft_remove_inside_corners": false,
    "raft_surface_layers": 2,
    "raft_surface_remove_inside_corners": false,
    "retraction_combing": "all",
    "retraction_during_travel_ratio": 0,
    "retraction_enable": true,
    "retraction_hop_after_extruder_switch": true,
    "retraction_hop_enabled": false,
    "roofing_layer_count": 0,
    "roofing_pattern": "lines",
    "scarf_joint_seam_length": 0,
    "skin_support": true,
    "small_hole_max_size": 0,
    "small_skin_width": 1,
    "speed_slowdown_layers": 2,
    "support_bottom_enable": false,
    "support_bottom_pattern": "concentric",
    "support_bottom_stair_step_height": 0.3,
    "support_brim_enable": true,
    "support_conical_angle": 30,
    "support_conical_enabled": false,
    "support_enable": false,
    "support_fan_enable": false,
    "support_infill_rate": 15,
    "support_interface_enable": false,
    "support_interface_pattern": "concentric",
    "support_line_distance": 2.66,
    "support_mesh": false,
    "support_meshes_present": false,
    "support_pattern": "zigzag",
    "support_roof_enable": false,
    "support_roof_pattern": "concentric",
    "support_skip_some_zags": false,
    "support_structure": "normal",
    "support_tree_limit_branch_reach": true,
    "support_type": "everywhere",
    "support_use_towers": true,
    "support_xy_overrides_z": "z_overrides_xy",
    "support_z_seam_away_from_model": true,
    "top_bottom_pattern": "lines",
    "top_bottom_pattern_0": "lines",
    "top_layers": 8,
    "top_skin_expand_distance": 1,
    "travel_avoid_other_parts": true,
    "wall_0_end_speed_ratio": 100.0,
    "wall_0_start_speed_ratio": 100.0,
    "wall_overhang_angle": 90,
    "wall_x_extruder_nr": -1,
    "wipe_hop_enable": true,
    "wipe_retraction_enable": true,
    "z_seam_type": "sharpest_corner",
    "zig_zaggify_infill": false
  },
  "variables": [
    "acceleration_enabled",
    "acceleration_travel_enabled",
    "adaptive_layer_height_enabled",
    "adhesion_type",
    "bottom_layers",
    "bottom_skin_expand_distance",
    "bridge_enable_more_layers",
    "bridge_settings_enabled",
    "build_volume_fan_nr",
    "carve_multiple_volumes",
    "clean_between_layers",
    "coasting_enable",
    "conical_overhang_enabled",
    "cool_fan_enabled",
    "cool_min_layer_time",
    "draft_shield_enabled",
    "draft_shield_height_limitation",
    "extruders_enabled_count",
    "fill_outline_gaps",
    "flooring_layer_count",
    "flooring_pattern",
    "gradual_flow_enabled",
    "gradual_infill_steps",
    "gradual_support_infill_steps",
    "hole_xy_offset",
    "infill_extruder_nr",
    "infill_line_distance",
    "infill_multiplier",
    "infill_pattern",
    "infill_sparse_density",
    "infill_support_enabled",
    "infill_wall_line_count",
    "initial_bottom_layers",
    "interlocking_enable",
    "ironing_enabled",
    "ironing_pattern",
    "jerk_enabled",
    "jerk_travel_enabled",
    "machine_extruders_share_heater",
    "machine_extruders_share_nozzle",
    "machine_firmware_retract",
    "machine_gcode_flavor",
    "machine_heated_bed",
    "machine_heated_build_volume",
    "machine_nozzle_temp_enabled",
    "magic_fuzzy_skin_enabled",
    "magic_spiralize",
    "material_final_print_temperature",
    "material_print_temperature",
    "meshfix_fluid_motion_enabled",
    "mold_enabled",
    "ooze_shield_enabled",
    "ppr_enable",
    "prime_tower_brim_enable",
    "prime_tower_enable",
    "prime_tower_mode",
    "print_sequence",
    "raft_base_remove_inside_corners",
    "raft_interface_layers",
    "raft_interface_remove_inside_corners",
    "raft_remove_inside_corners",
    "raft_surface_layers",
    "raft_surface_remove_inside_corners",
    "retraction_combing",
    "retraction_during_travel_ratio",
    "retraction_enable",
    "retraction_hop_after_extruder_switch",
    "retraction_hop_enabled",
    "roofing_layer_count",
    "roofing_pattern",
    "scarf_joint_seam_length",
    "skin_support",
    "small_hole_max_size",
    "small_skin_width",
    "speed_slowdown_layers",
    "support_bottom_enable",
    "support_bottom_pattern",
    "support_bottom_stair_step_height",
    "support_brim_enable",
    "support_conical_angle",
    "support_conical_enabled",
    "support_enable",
    "support_fan_enable",
    "support_infill_rate",
    "support_interface_enable",
    "support_interface_pattern",
    "support_line_distance",
    "support_mesh",
    "support_meshes_present",
    "support_pattern",
    "support_roof_enable",
    "support_roof_pattern",
    "support_skip_some_zags",
    "support_structure",
    "support_tree_limit_branch_reach",
    "support_type",
    "support_use_towers",
    "support_xy_overrides_z",
    "support_z_seam_away_from_model",
    "top_bottom_pattern",
    "top_bottom_pattern_0",
    "top_layers",
    "top_skin_expand_distance",
    "travel_avoid_other_parts",
    "wall_0_end_speed_ratio",
    "wall_0_start_speed_ratio",
    "wall_overhang_angle",
    "wall_x_extruder_nr",
    "wipe_hop_enable",
    "wipe_retraction_enable",
    "z_seam_type",
    "zig_zaggify_infill"
  ]
}
